conceptnet_rocks/__init__.py
conceptnet_rocks/cli.py
conceptnet_rocks/conceptnet5/__init__.py
conceptnet_rocks/conceptnet5/edges.py
conceptnet_rocks/conceptnet5/nodes.py
conceptnet_rocks/conceptnet5/prepare_data.py
conceptnet_rocks/conceptnet5/relations.py
conceptnet_rocks/conceptnet5/uri.py
conceptnet_rocks/database.py
conceptnet_rocks-0.1.2.dist-info/entry_points.txt
conceptnet_rocks-0.1.2.dist-info/LICENSE
conceptnet_rocks-0.1.2.dist-info/WHEEL
conceptnet_rocks-0.1.2.dist-info/METADATA
conceptnet_rocks-0.1.2.dist-info/RECORD
