Metadata-Version: 2.1
Name: conceptnet-rocks
Version: 0.1.2
Summary: Python library to work with ConceptNet offline
Home-page: https://github.com/ldtoolkit/conceptnet-rocks
License: Apache-2.0
Keywords: arangodb,conceptnet
Author: Roman Inflianskas
Author-email: infroma@gmail.com
Requires-Python: >=3.7,<4.0
Classifier: License :: OSI Approved :: Apache Software License
Classifier: Programming Language :: Python :: 3
Classifier: Programming Language :: Python :: 3.7
Classifier: Programming Language :: Python :: 3.8
Classifier: Topic :: Database
Requires-Dist: dask[dataframe] (>=2.27.0,<3.0.0)
Requires-Dist: graph-garden (>=0.1.2,<0.2.0)
Requires-Dist: orjson (>=3.3.1,<4.0.0)
Requires-Dist: python-arango (>=6.0.0,<7.0.0)
Requires-Dist: tqdm (>=4.48.2,<5.0.0)
Requires-Dist: typer (>=0.3.2,<0.4.0)
Project-URL: Repository, https://github.com/ldtoolkit/conceptnet-rocks
